ontodev_valve-0.2.1.dist-info/METADATA
ontodev_valve-0.2.1.dist-info/WHEEL
ontodev_valve-0.2.1.dist-info/license_files/LICENSE
ontodev_valve/__init__.py
ontodev_valve/ontodev_valve.cpython-39-darwin.so
ontodev_valve-0.2.1.dist-info/RECORD
