Metadata-Version: 2.1
Name: ontodev_valve
Version: 0.2.1
License-File: LICENSE
Summary: VALVE bindings for Python
Author: Knocean Inc.
License: BSD-3-Clause
Requires-Python: >=3.8
Project-URL: Homepage, https://github.com/ontodev/valve.py
